[
  {
    "slug": "flaeskestegssandwich",
    "title": "Flæskestegssandwich",
    "time": "15 min",
    "category": "sandwich",
    "tags": ["jul", "julefrokost", "sandwich"],
    "image": "flaeskestegssandwich-768x768.jpg"
  },
  {
    "slug": "vegetar-tarteletter",
    "title": "Vegetar tarteletter",
    "time": "45 min",
    "category": "forret",
    "tags": ["jul", "julefrokost", "forret"],
    "image": "vegetar-tarteletter-768x768.jpg"
  },
  {
    "slug": "fiskefilet",
    "title": "Fiskefilet i airfryer",
    "time": "20 min",
    "category": "frokost",
    "tags": ["jul", "julefrokost", "frokost"],
    "image": "fiskefilet-768x768.jpg"
  },
  {
    "slug": "frikadeller-juleudgave",
    "title": "Julefrikadeller i airfryer",
    "time": "31 min",
    "category": "frokost",
    "tags": ["jul", "julefrokost", "frokost"],
    "image": "frikadeller-768x768.jpg"
  }
]
